{
  "element": "Wall",
  "recipe": "Stone + Stone =\u003e Wall",
  "children": [
    {
      "element": "Stone",
      "recipe": "Pressure + Earth =\u003e Stone",
      "children": [
        {
          "element": "Pressure",
          "recipe": "Air + Air =\u003e Pressure",
          "children": [
            {
              "element": "Air",
              "recipe": "Air",
              "children": null
            },
            {
              "element": "Air",
              "recipe": "Air",
              "children": null
            }
          ]
        },
        {
          "element": "Earth",
          "recipe": "Earth",
          "children": null
        }
      ]
    },
    {
      "element": "Stone",
      "recipe": "Pressure + Earth =\u003e Stone",
      "children": [
        {
          "element": "Pressure",
          "recipe": "Air + Air =\u003e Pressure",
          "children": [
            {
              "element": "Air",
              "recipe": "Air",
              "children": null
            },
            {
              "element": "Air",
              "recipe": "Air",
              "children": null
            }
          ]
        },
        {
          "element": "Earth",
          "recipe": "Earth",
          "children": null
        }
      ]
    }
  ]
}